optical_features.py
radar_features.py
sentinel_satellites.py
sentinel_satellites-0.0.16.dist-info/LICENSE
sentinel_satellites-0.0.16.dist-info/METADATA
sentinel_satellites-0.0.16.dist-info/WHEEL
sentinel_satellites-0.0.16.dist-info/top_level.txt
sentinel_satellites-0.0.16.dist-info/RECORD
