Metadata-Version: 2.1
Name: sentinel-satellites
Version: 0.0.16
Summary: A Python library that allows to extract data from sentinel satellites, exploiting multi-threading and relying on Google Earth Engine APIs.
Home-page: https://github.com/Amatofrancesco99/master-thesis/tree/main/Notebooks/utils
Author: Francesco Amato
Author-email: amatofrancesco99@gmail.com
License: mit
Classifier: Programming Language :: Python :: 3
Classifier: License :: OSI Approved :: MIT License
Classifier: Operating System :: OS Independent
Classifier: Development Status :: 3 - Alpha
Classifier: Intended Audience :: Developers
License-File: LICENSE
Requires-Dist: earthengine-api
Requires-Dist: pandas
